payfast/__init__.py
payfast/apps.py
payfast/base.py
payfast/callbacks.py
payfast/conf.py
payfast/constants.py
payfast/decorators.py
payfast/exceptions.py
payfast/itn.py
payfast/logging.py
payfast/payment.py
payfast/security_checks.py
payfast/serialization.py
payfast/signals.py
payfast/signature.py
payfast/templates.py
payfast/timezone.py
payfast/urls.py
payfast/utils.py
payfast/validation.py
payfast/views.py
payfast/api/__init__.py
payfast/api/refunds.py
payfast/api/subscriptions.py
payfast/api/transactions.py
payfast/templates/payfast/form.html
payfast/templates/payfast/sandbox.html
tests/__init__.py
tests/test_base.py
tests/test_callbacks.py
tests/test_conf.py
tests/test_constants.py
tests/test_exceptions.py
tests/test_itn.py
tests/test_payfast.py
tests/test_payment.py
tests/test_security_checks.py
tests/test_signature.py
tests/test_templates.py
tests/test_timezone.py
tests/test_utils.py
tests/api/__init__.py
tests/api/test_subscriptions.py
tests/api/test_transactions.py
python_payfast-0.6.1.dist-info/LICENSE
python_payfast-0.6.1.dist-info/METADATA
python_payfast-0.6.1.dist-info/WHEEL
python_payfast-0.6.1.dist-info/top_level.txt
python_payfast-0.6.1.dist-info/RECORD
